Metadata-Version: 2.1
Name: xlsxColumnRow
Version: 2.0.0
Summary: xlsx Package
Home-page: UNKNOWN
Author: codingChamp
Author-email: codingChamp@gmail.com
License: MIT
Keywords: pypi
Platform: UNKNOWN
Classifier: Development Status :: 3 - Alpha
Classifier: Intended Audience :: Developers
Classifier: Topic :: Software Development :: Documentation
Classifier: License :: OSI Approved :: MIT License
Classifier: Programming Language :: Python :: 3
Classifier: Programming Language :: Python :: 3.7
Classifier: Programming Language :: Python :: 3.8
Classifier: Programming Language :: Python :: 3.9
License-File: LICENSE.txt
